gpt3_simple_primer/__init__.py
gpt3_simple_primer/examples.py
gpt3_simple_primer/generator.py
gpt3_simple_primer-0.1.2.dist-info/LICENSE
gpt3_simple_primer-0.1.2.dist-info/METADATA
gpt3_simple_primer-0.1.2.dist-info/WHEEL
gpt3_simple_primer-0.1.2.dist-info/top_level.txt
gpt3_simple_primer-0.1.2.dist-info/RECORD
