Metadata-Version: 2.1
Name: gpt3-simple-primer
Version: 0.1.2
Summary: GPT-3 wrapper for Python
Home-page: https://github.com/happilyeverafter95/gpt-3
Author: happilyeverafter95
Author-email: author@example.com
License: UNKNOWN
Project-URL: Bug Tracker, https://github.com/happilyeverafter95/gpt-3/issues
Keywords: gpt-3,text generation,language model,priming
Platform: UNKNOWN
Classifier: Programming Language :: Python :: 3
Classifier: License :: OSI Approved :: MIT License
Classifier: Operating System :: OS Independent
Requires-Python: >=3.7.1
Requires-Dist: openai (==0.11.0)
